bukowski/__init__.py
bukowski/cli.py
bukowski/factory.py
bukowski/main.py
bukowski-0.3.7.dist-info/METADATA
bukowski-0.3.7.dist-info/WHEEL
bukowski-0.3.7.dist-info/entry_points.txt
bukowski-0.3.7.dist-info/licenses/LICENSE
bukowski-0.3.7.dist-info/RECORD
