Metadata-Version: 2.4
Name: bukowski
Version: 0.3.7
Summary: A pyproject.toml conversion tool for Poetry to uv migration
Project-URL: Repository, https://github.com/ninoseki/bukowski
License: MIT License
License-File: LICENSE
Keywords: poetry,uv
Classifier: License :: OSI Approved :: MIT License
Classifier: Programming Language :: Python
Classifier: Programming Language :: Python :: 3.10
Classifier: Programming Language :: Python :: 3.11
Classifier: Programming Language :: Python :: 3.12
Requires-Python: >=3.10
Requires-Dist: poetry<1.9.0,>=1.8.3
Requires-Dist: returns~=0.23
Requires-Dist: tomlkit~=0.13
Requires-Dist: typer~=0.14
